setup.py
NAlpha/__init__.py
NAlpha.egg-info/PKG-INFO
NAlpha.egg-info/SOURCES.txt
NAlpha.egg-info/dependency_links.txt
NAlpha.egg-info/not-zip-safe
NAlpha.egg-info/top_level.txt
NAlpha/CTP/ApiConst.py
NAlpha/CTP/ApiStruct.py
NAlpha/CTP/FutureAccount.py
NAlpha/CTP/MdApi.py
NAlpha/CTP/ReqAuthenticate.py
NAlpha/CTP/TraderApi.py
NAlpha/CTP/__init__.py
NAlpha/ta/__init__.py
NAlpha/ta/time_bar.py
NAlpha/utils/__init__.py
NAlpha/utils/base_field.py
NAlpha/utils/check_service.py
D:/Projects/NAlpha/src/NAlpha/CTP/MdApiBase.cpp
D:/Projects/NAlpha/src/NAlpha/CTP/TraderApiBase.cpp
D:/Projects/NAlpha/src/NAlpha/CTP/api/v6.3.15/windows64/thostmduserapi_se.dll
D:/Projects/NAlpha/src/NAlpha/CTP/api/v6.3.15/windows64/thosttraderapi_se.dll